{
  "type": "FeatureCollection",
  "features": [
    {
      "type": "Feature",
      "geometry": {
        "type": "Polygon",
        "coordinates": [
          [
            [
              31.806187036975615,
              36.59978870768168
            ],
            [
              31.806332550689326,
              36.599719145535204
            ],
            [
              31.806270187669163,
              36.59963567082572
            ],
            [
              31.80621128904977,
              36.59964680074974
            ],
            [
              31.80622861232239,
              36.59967462574386
            ],
            [
              31.806110815400803,
              36.59969410313185
            ],
            [
              31.8061269889405,
              36.59971417738491
            ],
            [
              31.806187036975615,
              36.59978870768168
            ]
          ]
        ]
      },
      "properties": {
        "area_m2": 263,
        "name": "test bina",
        "category": "building",
        "desc": "https://markokara.github.io/leaflet-blue-dot/admin.html menü için tıkla",
        "image": "https://www.dimitriseconomou.com/wp-content/uploads/2019/06/OLIVETREE1687.jpg",
        "stroke": "#00FF00",
        "fill": "#00FF00",
        "height": 25,
        "levels": 3,
        "building:levels": 3,
        "fill_op": 0.01,
        "stroke_op": 0.001
      },
      "id": "c19eb151-c516-411e-9532-f28491d075a4"
    },
    {
      "type": "Feature",
      "geometry": {
        "type": "LineString",
        "coordinates": [
          [
            31.805962994699545,
            36.59971109647145
          ],
          [
            31.806383945085617,
            36.5995177132578
          ],
          [
            31.80641883776832,
            36.59949979213832
          ],
          [
            31.806430726675682,
            36.599493685913544
          ]
        ]
      },
      "properties": {
        "len_m": 48,
        "name": "test yol",
        "category": "path",
        "way": "foot"
      },
      "id": "0dcec35e-787f-4c09-a21b-98f9a5ed368c"
    },
    {
      "type": "Feature",
      "geometry": {
        "type": "Polygon",
        "coordinates": [
          [
            [
              31.00736658476179,
              36.864338681872326
            ],
            [
              31.00736135757083,
              36.86427034966768
            ],
            [
              31.007411887110017,
              36.86427034966768
            ],
            [
              31.007420599041772,
              36.86420480649603
            ],
            [
              31.007485067783428,
              36.86420341194895
            ],
            [
              31.007485067783428,
              36.86416157581307
            ],
            [
              31.00758612686179,
              36.86416157581307
            ],
            [
              31.007587869152427,
              36.86419643927721
            ],
            [
              31.00753733969301,
              36.86419643927721
            ],
            [
              31.007593096343385,
              36.86419783379246
            ],
            [
              31.007593096343385,
              36.864235486269195
            ],
            [
              31.007535597242846,
              36.864238275362084
            ],
            [
              31.007542566883966,
              36.86429545129708
            ],
            [
              31.007511203738215,
              36.86429545129708
            ],
            [
              31.007511203738215,
              36.86433728732774
            ],
            [
              31.00736658476179,
              36.864338681872326
            ]
          ]
        ]
      },
      "properties": {
        "area_m2": 386,
        "name": "test bina",
        "category": "building",
        "fill_op": 0.001
      },
      "id": "5d3aad87-a24e-4009-b4ae-e58c78233789"
    }
  ]
}
